setup.py
autoprotege.egg-info/PKG-INFO
autoprotege.egg-info/SOURCES.txt
autoprotege.egg-info/dependency_links.txt
autoprotege.egg-info/top_level.txt
ontApi/__init__.py
ontApi/owlApiv1.py
ontApi/owlApiv2.py
ontModel/__init__.py
ontModel/dataProperty.py
ontModel/generalAxioms.py
ontModel/individual.py
ontModel/objectProperty.py
ontModel/oneClass.py
ontTool/__init__.py
ontTool/initial_owl.py
ontTool/merge_owl.py
ontTool/read_owl.py
ontTool/split_owl.py
ontTool/write_owl.py